{
  "version": "1.0.0",
  "generatedAt": "2025-11-13T19:21:01.523Z",
  "categories": {
    "ECUT": {
      "name": "ECUT",
      "excelFile": "E-Cut készlet.xlsx",
      "toolCount": 29,
      "codePatterns": [
        "8400",
        "8410",
        "8420"
      ],
      "tools": [
        {
          "toolCode": "RT-8400300",
          "codePrefix": "8400",
          "description": "",
          "diameter": null
        },
        {
          "toolCode": "RT-8400391_1",
          "codePrefix": "8400",
          "description": "",
          "diameter": null
        },
        {
          "toolCode": "RT-8400391",
          "codePrefix": "8400",
          "description": "",
          "diameter": null
        },
        {
          "toolCode": "RT-8400450",
          "codePrefix": "8400",
          "description": "",
          "diameter": null
        },
        {
          "toolCode": "RT-8400450_1",
          "codePrefix": "8400",
          "description": "",
          "diameter": null
        }
      ],
      "diameterRange": {
        "min": null,
        "max": null
      }
    },
    "MFC": {
      "name": "MFC",
      "excelFile": "MFC készlet.xlsx",
      "toolCount": 28,
      "codePatterns": [
        "8201",
        "8211",
        "8221"
      ],
      "tools": [
        {
          "toolCode": "RT-8201300",
          "codePrefix": "8201",
          "description": "",
          "diameter": null
        },
        {
          "toolCode": "RT-8201391",
          "codePrefix": "8201",
          "description": "",
          "diameter": null
        },
        {
          "toolCode": "RT-8201391_1",
          "codePrefix": "8201",
          "description": "",
          "diameter": null
        },
        {
          "toolCode": "RT-8201450",
          "codePrefix": "8201",
          "description": "",
          "diameter": null
        },
        {
          "toolCode": "RT-8201450_1",
          "codePrefix": "8201",
          "description": "",
          "diameter": null
        }
      ],
      "diameterRange": {
        "min": null,
        "max": null
      }
    },
    "XF": {
      "name": "XF",
      "excelFile": "XF simitó.xlsx",
      "toolCount": 37,
      "codePatterns": [
        "1525",
        "8521"
      ],
      "tools": [
        {
          "toolCode": "RT-15250300",
          "codePrefix": "1525",
          "description": "",
          "diameter": null
        },
        {
          "toolCode": "RT-15250391",
          "codePrefix": "1525",
          "description": "",
          "diameter": null
        },
        {
          "toolCode": "RT-15250391_1",
          "codePrefix": "1525",
          "description": "",
          "diameter": null
        },
        {
          "toolCode": "RT-15250450",
          "codePrefix": "1525",
          "description": "",
          "diameter": null
        },
        {
          "toolCode": "RT-15250450_1",
          "codePrefix": "1525",
          "description": "",
          "diameter": null
        }
      ],
      "diameterRange": {
        "min": null,
        "max": null
      }
    },
    "XFEED": {
      "name": "XFEED",
      "excelFile": "XFeed szerszámok.xlsx",
      "toolCount": 0,
      "codePatterns": [],
      "tools": [],
      "diameterRange": {
        "min": null,
        "max": null
      }
    }
  },
  "matchingRules": {
    "description": "Match tools by category code prefix (4 digits after RT-) and diameter",
    "ignoreVariants": "Tool codes with _1, _2 suffixes are variants of the same tool",
    "diameterTolerance": 0.01,
    "examples": [
      {
        "matrixCode": "RT-8400300",
        "category": "ECUT",
        "codePrefix": "8400",
        "diameter": 5.7,
        "description": "ø5,7/6x56/12 r0.1 z4"
      }
    ]
  }
}